LICENSE
README.md
pyproject.toml
setup.py
pcollections/__init__.py
pcollections/_dict.py
pcollections/_lazy.py
pcollections/_list.py
pcollections/_set.py
pcollections.egg-info/PKG-INFO
pcollections.egg-info/SOURCES.txt
pcollections.egg-info/dependency_links.txt
pcollections.egg-info/not-zip-safe
pcollections.egg-info/requires.txt
pcollections.egg-info/top_level.txt
pcollections/abc/__init__.py
pcollections/abc/_core.py
pcollections/abc/_map.py
pcollections/abc/_seq.py
pcollections/abc/_set.py
pcollections/test/__init__.py
pcollections/test/__main__.py
pcollections/test/_dict.py
pcollections/test/_list.py
pcollections/test/_set.py
pcollections/util/__init__.py
pcollections/util/_core.py