Metadata-Version: 2.4
Name: pcollections
Version: 0.4.0
Summary: A persistent collections library for Python
Home-page: https://github.com/noahbenson/pcollections/
Download-URL: https://github.com/noahbenson/pcollections/
Author: Noah C. Benson
Author-email: "Noah C. Benson" <nben@uw.edu>
License: MIT License
Project-URL: homepage, https://github.com/noahbenson/pcollections
Project-URL: documentation, https://github.com/noahbenson/pcollections
Project-URL: repository, https://github.com/noahbenson/pcollections
Keywords: persistent,immutable,functional,lazy
Classifier: Intended Audience :: Developers
Classifier: License :: OSI Approved :: MIT License
Classifier: Programming Language :: Python :: 3
Classifier: Programming Language :: Python :: 3.7
Classifier: Programming Language :: Python :: 3.8
Classifier: Programming Language :: Python :: 3.9
Classifier: Programming Language :: Python :: 3.10
Classifier: Programming Language :: Python :: 3.11
Classifier: Programming Language :: Python :: 3.12
Classifier: Programming Language :: Python :: 3.13
Classifier: Topic :: Software Development
Classifier: Topic :: Software Development :: Libraries
Classifier: Topic :: Software Development :: Libraries :: Python Modules
Classifier: Operating System :: Microsoft :: Windows
Classifier: Operating System :: POSIX
Classifier: Operating System :: Unix
Classifier: Operating System :: MacOS
Requires-Python: >=3.7
License-File: LICENSE
Requires-Dist: phamt>=0.1.7
Dynamic: author
Dynamic: download-url
Dynamic: home-page
Dynamic: license-file
